trading_utils/__init__.py
trading_utils/logger/__init__.py
trading_utils/thread_manager/__init__.py
trading_utils/thread_manager/smiley.py
trading_utils_test-0.0.3.dist-info/METADATA
trading_utils_test-0.0.3.dist-info/WHEEL
trading_utils_test-0.0.3.dist-info/RECORD
