Metadata-Version: 2.1
Name: trading-utils-test
Version: 0.0.3
Summary: 
Author: Trading IT
Requires-Python: >=3.9,<4.0
Classifier: Programming Language :: Python :: 3
Classifier: Programming Language :: Python :: 3.9
Classifier: Programming Language :: Python :: 3.10
Classifier: Programming Language :: Python :: 3.11
Requires-Dist: json-log-formatter (>=0.5.2,<0.6.0)
